lj/__init__.py
lj/backup.py
lj/lj.py
lj-0.2.dist-info/DESCRIPTION.rst
lj-0.2.dist-info/METADATA
lj-0.2.dist-info/RECORD
lj-0.2.dist-info/WHEEL
lj-0.2.dist-info/metadata.json
lj-0.2.dist-info/top_level.txt
