Metadata-Version: 2.0
Name: lj
Version: 0.2
Summary: Python realization of LiveJournal (LJ) API.Checkout https://github.com/daniilr/python-lj for more info
Home-page: https://github.com/daniilr/python-lj
Author: Original developer: David Lynch; Curent maintainer: Daniil Ryzhkov 
Author-email: i@daniil-r.ru
License: The BSD 3-Clause License
Download-URL: https://github.com/daniilr/python-lj/tarball/0.2
Keywords: livejournal,blog,writing
Platform: osx
Platform: posix
Platform: linux
Platform: windows
